nonebot_plugin_chatgpt_api/__init__.py
nonebot_plugin_chatgpt_api/chatgpt_api.py
nonebot_plugin_chatgpt_api/chatgpt_stats.py
nonebot_plugin_chatgpt_api/config.py
nonebot_plugin_chatgpt_api/data_storage.py
nonebot_plugin_chatgpt_api/scheduled_jobs.py
nonebot_plugin_chatgpt_api/utils.py
nonebot_plugin_chatgpt_api/command/__init__.py
nonebot_plugin_chatgpt_api/command/chat.py
nonebot_plugin_chatgpt_api/command/chat_recover.py
nonebot_plugin_chatgpt_api/command/chat_refresh.py
nonebot_plugin_chatgpt_api/command/help.py
nonebot_plugin_chatgpt_api/command/system_prompt.py
nonebot_plugin_chatgpt_api/matcher/__init__.py
nonebot_plugin_chatgpt_api/matcher/enhanced_matcher.py
nonebot_plugin_chatgpt_api/rule/__init__.py
nonebot_plugin_chatgpt_api/rule/notstartswith.py
nonebot_plugin_chatgpt_api-1.1.5.dist-info/LICENSE
nonebot_plugin_chatgpt_api-1.1.5.dist-info/METADATA
nonebot_plugin_chatgpt_api-1.1.5.dist-info/WHEEL
nonebot_plugin_chatgpt_api-1.1.5.dist-info/top_level.txt
nonebot_plugin_chatgpt_api-1.1.5.dist-info/RECORD
