Metadata-Version: 2.1
Name: nonebot-plugin-chatgpt-api
Version: 1.1.5
Summary: NoneBot2 plugin for AI chat with OpenAI API.
Author-email: SanJerry007 <sandy375408563@gmail.com>
License: MIT
Project-URL: Homepage, https://github.com/SanJerry007/nonebot-plugin-chatgpt-api
Project-URL: Repository, https://github.com/SanJerry007/nonebot-plugin-chatgpt-api
Requires-Python: >=3.9
License-File: LICENSE
Requires-Dist: nonebot2>=2.4.1
Requires-Dist: nonebot-adapter-onebot>=2.2.4
Requires-Dist: nonebot-plugin-localstore>=0.7.3
Requires-Dist: nonebot-plugin-apscheduler>=0.5.0
Requires-Dist: nonebot-plugin-htmlrender>=0.6.0
Requires-Dist: openai>=1.2.4
Requires-Dist: pandas>=2.2.3
Requires-Dist: httpx>=0.28.1
